LICENSE
MANIFEST.in
README.rst
requirements.txt
setup.cfg
setup.py
ckanext/__init__.py
ckanext/pgda_gt_theme/__init__.py
ckanext/pgda_gt_theme/plugin.py
ckanext/pgda_gt_theme/fanstatic/init.js
ckanext/pgda_gt_theme/fanstatic/styles.css
ckanext/pgda_gt_theme/public/img/cat1.png
ckanext/pgda_gt_theme/public/img/cat10.png
ckanext/pgda_gt_theme/public/img/cat11.png
ckanext/pgda_gt_theme/public/img/cat12.png
ckanext/pgda_gt_theme/public/img/cat13.png
ckanext/pgda_gt_theme/public/img/cat2.png
ckanext/pgda_gt_theme/public/img/cat3.png
ckanext/pgda_gt_theme/public/img/cat4.png
ckanext/pgda_gt_theme/public/img/cat5.png
ckanext/pgda_gt_theme/public/img/cat6.png
ckanext/pgda_gt_theme/public/img/cat7.png
ckanext/pgda_gt_theme/public/img/cat8.png
ckanext/pgda_gt_theme/public/img/cat9.png
ckanext/pgda_gt_theme/public/img/logo.png
ckanext/pgda_gt_theme/public/img/red.png
ckanext/pgda_gt_theme/public/img/search-trans.png
ckanext/pgda_gt_theme/public/img/search.png
ckanext/pgda_gt_theme/public/img/slider.png
ckanext/pgda_gt_theme/templates/base.html
ckanext/pgda_gt_theme/templates/footer.html
ckanext/pgda_gt_theme/templates/header.html
ckanext/pgda_gt_theme/templates/page.html
ckanext/pgda_gt_theme/templates/home/index.html
ckanext/pgda_gt_theme/templates/home/layout1.html
ckanext/pgda_gt_theme/templates/home/snippets/promoted.html
ckanext/pgda_gt_theme/tests/__init__.py
ckanext/pgda_gt_theme/tests/test_plugin.py
ckanext_pgda_gt_theme.egg-info/PKG-INFO
ckanext_pgda_gt_theme.egg-info/SOURCES.txt
ckanext_pgda_gt_theme.egg-info/dependency_links.txt
ckanext_pgda_gt_theme.egg-info/entry_points.txt
ckanext_pgda_gt_theme.egg-info/namespace_packages.txt
ckanext_pgda_gt_theme.egg-info/top_level.txt