Metadata-Version: 1.1
Name: ckanext-pgda-gt-theme
Version: 0.0.2
Summary: Tema para el portal general de datos abiertos
Home-page: https://github.com/RedCiudadana/ckanext-pgda_gt_theme
Author: Red Ciudadana
Author-email: info@redciudadana.org
License: AGPL
Keywords: CKAN guatemala portal general datos abiertos
Platform: UNKNOWN
Classifier: Development Status :: 4 - Beta
Classifier: License :: OSI Approved :: GNU Affero General Public License v3 or later (AGPLv3+)
Classifier: Programming Language :: Python :: 2.7
